django_backup/__init__.py
django_backup/admin.py
django_backup/apps.py
django_backup/models.py
django_backup/scheduler.py
django_backup/backup/__init__.py
django_backup/backup/postgres.py
django_backup/backup/s3.py
django_backup/backup/utils.py
django_backup/management/__init__.py
django_backup/management/commands/__init__.py
django_backup/management/commands/run_backup.py
django_postgres_backup_ganaf-0.1.2.dist-info/LICENCE
django_postgres_backup_ganaf-0.1.2.dist-info/METADATA
django_postgres_backup_ganaf-0.1.2.dist-info/WHEEL
django_postgres_backup_ganaf-0.1.2.dist-info/top_level.txt
django_postgres_backup_ganaf-0.1.2.dist-info/RECORD
