Metadata-Version: 2.2
Name: django-postgres-backup-ganaf
Version: 0.1.2
Summary: A Django app to backup PostgreSQL databases to S3
Home-page: https://github.com/yourusername/django-postgres-backup
Author: Your Name
Author-email: your.email@example.com
Project-URL: Bug Tracker, https://github.com/yourusername/django-postgres-backup/issues
Classifier: Development Status :: 4 - Beta
Classifier: Environment :: Web Environment
Classifier: Framework :: Django
Classifier: Framework :: Django :: 3.2
Classifier: Framework :: Django :: 4.0
Classifier: Framework :: Django :: 4.1
Classifier: Framework :: Django :: 4.2
Classifier: Intended Audience :: Developers
Classifier: License :: OSI Approved :: MIT License
Classifier: Operating System :: OS Independent
Classifier: Programming Language :: Python :: 3
Classifier: Programming Language :: Python :: 3.8
Classifier: Programming Language :: Python :: 3.9
Classifier: Programming Language :: Python :: 3.10
Classifier: Programming Language :: Python :: 3.11
Requires-Python: >=3.8
License-File: LICENCE
Requires-Dist: Django>=3.2
Requires-Dist: boto3>=1.26.0
Requires-Dist: apscheduler>=3.9.0
Dynamic: author
Dynamic: author-email
Dynamic: classifier
Dynamic: description
Dynamic: description-content-type
Dynamic: home-page
Dynamic: project-url
Dynamic: requires-dist
Dynamic: requires-python
Dynamic: summary
